aliyun_citybrain_sdk/__init__.py
aliyun_citybrain_sdk/client.py
aliyun_citybrain_sdk/auth/__init__.py
aliyun_citybrain_sdk/auth/sign_tool.py
aliyun_citybrain_sdk/http_model/__init__.py
aliyun_citybrain_sdk/http_model/http_request.py
aliyun_citybrain_sdk/http_model/http_response.py
aliyun_citybrain_sdk-0.0.2.dist-info/LICENSE
aliyun_citybrain_sdk-0.0.2.dist-info/METADATA
aliyun_citybrain_sdk-0.0.2.dist-info/WHEEL
aliyun_citybrain_sdk-0.0.2.dist-info/top_level.txt
aliyun_citybrain_sdk-0.0.2.dist-info/RECORD
