Metadata-Version: 2.1
Name: aliyun-citybrain-sdk
Version: 0.0.2
Summary: 阿里云交通云控平台SDK
Home-page: UNKNOWN
Author: fanyubin
Author-email: fanyubin@jiagouyun.com
License: UNKNOWN
Platform: UNKNOWN
Classifier: Programming Language :: Python :: 3
Classifier: License :: OSI Approved :: MIT License
Classifier: Operating System :: OS Independent
Requires-Python: >=3.6
